Metadata-Version: 1.0
Name: Gaussandbinomial
Version: 0.3
Summary: Gaussian and Binomial distributions
Home-page: UNKNOWN
Author: Pranali Parab
Author-email: UNKNOWN
License: UNKNOWN
Platform: UNKNOWN
